u_random_dummy_data/__init__.py
u_random_dummy_data/__main__.py
u_random_dummy_data/format.py
u_random_dummy_data/generate_dummy_data.py
u_random_dummy_data-0.2.1.dist-info/METADATA
u_random_dummy_data-0.2.1.dist-info/WHEEL
u_random_dummy_data-0.2.1.dist-info/entry_points.txt
u_random_dummy_data-0.2.1.dist-info/licenses/LICENSE
u_random_dummy_data-0.2.1.dist-info/RECORD
