Metadata-Version: 2.1
Name: u_random_dummy_data
Version: 0.2.1
Summary: これは様々なフィールドのランダムダミーデータを生成するためのPythonアプリケーションです。
Project-URL: Repository, https://github.com/h-keisuke/uRandomDummyData
Project-URL: Issues, https://github.com/h-keisuke/uRandomDummyData/issues
Author-email: Keisuke HANAMURA <hkeisuke75@gmail.com>
License-File: LICENSE
Requires-Python: ~=3.9
Requires-Dist: argparse>=1.4.0
Requires-Dist: faker>=23.2.1
Requires-Dist: pykakasi>=2.2.1
Requires-Dist: pyyaml>=6.0.1
